MANIFEST.in
README.rst
setup.cfg
setup.py
versioneer.py
panel_plots.egg-info/PKG-INFO
panel_plots.egg-info/SOURCES.txt
panel_plots.egg-info/dependency_links.txt
panel_plots.egg-info/requires.txt
panel_plots.egg-info/top_level.txt
panels/__init__.py
panels/_locators.py
panels/_units.py
panels/_version.py
panels/tests/__init__.py
panels/tests/test_FigureSizeLocator.py
panels/tests/test_PanelSizeLocator.py
panels/tests/test_convert_units.py