Metadata-Version: 1.0
Name: panel-plots
Version: 0.1.0
Summary: Organize matplotlib plots in panels
Home-page: https://github.com/ajdawson/panel-plots
Author: Andrew Dawson
Author-email: UNKNOWN
License: GPL3
Platform: UNKNOWN
